phash/__init__.py
phash/phash_ctypes.py
phash-0.2.0.data/scripts/compare-images.py
phash-0.2.0.dist-info/DESCRIPTION.rst
phash-0.2.0.dist-info/METADATA
phash-0.2.0.dist-info/metadata.json
phash-0.2.0.dist-info/pbr.json
phash-0.2.0.dist-info/RECORD
phash-0.2.0.dist-info/top_level.txt
phash-0.2.0.dist-info/WHEEL
